easy_llama/__init__.py
easy_llama/formats.py
easy_llama/libllama.py
easy_llama/libmtmd.py
easy_llama/llama.py
easy_llama/newthread.py
easy_llama/sampling.py
easy_llama/server.py
easy_llama/thread.py
easy_llama/utils.py
easy_llama/webui/index.html
easy_llama/webui/script.js
easy_llama/webui/style.css
easy_llama-0.2.14.dist-info/licenses/LICENSE
easy_llama-0.2.14.dist-info/METADATA
easy_llama-0.2.14.dist-info/WHEEL
easy_llama-0.2.14.dist-info/top_level.txt
easy_llama-0.2.14.dist-info/RECORD
