Metadata-Version: 2.4
Name: easy_llama
Version: 0.2.14
Summary: Python package wrapping llama.cpp for on-device LLM inference
Author-email: Dylan Halladay <chemist-mulches-39@icloud.com>
License-Expression: MIT
Project-URL: Homepage, https://github.com/ddh0/easy-llama
Classifier: Development Status :: 4 - Beta
Classifier: Intended Audience :: Developers
Classifier: Intended Audience :: Science/Research
Classifier: Natural Language :: English
Classifier: Programming Language :: Python :: 3 :: Only
Classifier: Programming Language :: Python :: 3.9
Classifier: Programming Language :: Python :: 3.10
Classifier: Programming Language :: Python :: 3.11
Classifier: Programming Language :: Python :: 3.12
Requires-Python: >=3.9
License-File: LICENSE
Requires-Dist: numpy
Requires-Dist: fastapi
Requires-Dist: uvicorn
Requires-Dist: jinja2
Requires-Dist: tqdm
Dynamic: license-file
